README.md
setup.py
tools/__init__.py
tools/inference_image_detect.py
tools/inference_video_detect.py
tools/train_classifier.py
tools/train_detector.py
tools/utils/__init__.py
tools/utils/dataloaders.py
tools/utils/general.py
tools/utils/load_model.py
tools/utils/logging.py
tools/utils/transforms.py
tools/utils/detection/__init__.py
tools/utils/detection/datasets.py
vision_transformers/__init__.py
vision_transformers.egg-info/PKG-INFO
vision_transformers.egg-info/SOURCES.txt
vision_transformers.egg-info/dependency_links.txt
vision_transformers.egg-info/requires.txt
vision_transformers.egg-info/top_level.txt
vision_transformers/detection/__init__.py
vision_transformers/detection/detr/__init__.py
vision_transformers/detection/detr/model.py
vision_transformers/models/__init__.py
vision_transformers/models/mobile_vit.py
vision_transformers/models/swin_transformer.py
vision_transformers/models/vit.py
vision_transformers/models/layers/__init__.py
vision_transformers/models/layers/activation.py
vision_transformers/models/layers/attention.py
vision_transformers/models/layers/conv_bn_act.py
vision_transformers/models/layers/drop.py
vision_transformers/models/layers/global_pool.py
vision_transformers/models/layers/helpers.py
vision_transformers/models/layers/mlp.py
vision_transformers/models/layers/norm.py
vision_transformers/models/layers/patches.py
vision_transformers/models/layers/residual.py
vision_transformers/models/layers/transformer.py
vision_transformers/models/layers/weight_init.py
vision_transformers/utils/__init__.py
vision_transformers/utils/load_weights.py
vision_transformers/utils/params.py